{
  "kind": "collectionType",
  "collectionName": "posts",
  "info": {
    "singularName": "post",
    "pluralName": "posts",
    "displayName": "post"
  },
  "options": {
    "draftAndPublish": false
  },
  "pluginOptions": {},
  "attributes": {
    "title": {
      "type": "string"
    },
    "Content": {
      "type": "richtext"
    },
    "user": {
      "type": "relation",
      "relation": "manyToOne",
      "target": "plugin::users-permissions.user",
      "inversedBy": "posts"
    },
    "likers": {
      "type": "relation",
      "relation": "manyToMany",
      "target": "plugin::users-permissions.user",
      "inversedBy": "liked_posts"
    },
    "medias": {
      "allowedTypes": [
        "images",
        "files",
        "videos",
        "audios"
      ],
      "type": "media",
      "multiple": true
    }
  }
}
